abcd_pyhf/__init__.py
abcd_pyhf/abcd.py
abcd_pyhf/pool_utils.py
abcd_pyhf/pyhf_util.py
abcd_pyhf-0.0.7.dist-info/LICENSE
abcd_pyhf-0.0.7.dist-info/METADATA
abcd_pyhf-0.0.7.dist-info/WHEEL
abcd_pyhf-0.0.7.dist-info/top_level.txt
abcd_pyhf-0.0.7.dist-info/RECORD
