Metadata-Version: 2.2
Name: abcd-pyhf
Version: 0.0.7
Summary: pyhf implementation of the ABCD method for background estimation
Home-page: https://github.com/masonproffitt/abcd-pyhf
Author: Mason Proffitt
Author-email: masonlp@uw.edu
Classifier: Programming Language :: Python :: 3
Classifier: License :: OSI Approved :: MIT License
Classifier: Operating System :: OS Independent
Requires-Python: >=3.8
License-File: LICENSE
Requires-Dist: numpy
Requires-Dist: matplotlib
Requires-Dist: pyhf[contrib,minuit]>=0.7
Provides-Extra: test
Requires-Dist: flake8; extra == "test"
Requires-Dist: pytest; extra == "test"
